namebuster.py
namebuster-1.0.2.data/scripts/namebuster
utils/__init__.py
utils/nlp_parser.py
utils/request.py
namebuster-1.0.2.dist-info/LICENSE
namebuster-1.0.2.dist-info/METADATA
namebuster-1.0.2.dist-info/WHEEL
namebuster-1.0.2.dist-info/top_level.txt
namebuster-1.0.2.dist-info/RECORD
