Metadata-Version: 2.1
Name: namebuster
Version: 1.0.2
Summary: A tool for generating common username permutations from a list of names, a file, or url, to aid with username enumeration
Home-page: https://github.com/benbusby/namebuster
Author: Ben Busby
Author-email: contact@benbusby.com
License: UNKNOWN
Platform: UNKNOWN
Classifier: Programming Language :: Python :: 3
Classifier: License :: OSI Approved :: MIT License
Classifier: Operating System :: OS Independent
Requires-Dist: beautifulsoup4 (==4.9.0)
Requires-Dist: blis (==0.4.1)
Requires-Dist: bs4 (==0.0.1)
Requires-Dist: catalogue (==1.0.0)
Requires-Dist: certifi (==2020.4.5.1)
Requires-Dist: chardet (==3.0.4)
Requires-Dist: cymem (==2.0.3)
Requires-Dist: idna (==2.9)
Requires-Dist: importlib-metadata (==1.6.0)
Requires-Dist: murmurhash (==1.0.2)
Requires-Dist: numpy (==1.18.2)
Requires-Dist: plac (==1.1.3)
Requires-Dist: preshed (==3.0.2)
Requires-Dist: pycurl (==7.43.0.5)
Requires-Dist: requests (==2.23.0)
Requires-Dist: soupsieve (==2.0)
Requires-Dist: spacy (==2.2.4)
Requires-Dist: srsly (==1.0.2)
Requires-Dist: thinc (==7.4.0)
Requires-Dist: tqdm (==4.45.0)
Requires-Dist: urllib3 (==1.25.8)
Requires-Dist: wasabi (==0.6.0)
Requires-Dist: zipp (==3.1.0)
